{
  "recentFiles": [
    {
      "basename": "5.2.2 - Modelo TCP-IP",
      "path": "DAM-1/Sistemas informáticos/Tema 5 - Sistemas Informáticos en Red/5.2.2 - Modelo TCP-IP.md"
    },
    {
      "basename": "Tema 5 - Sistemas Informáticos en Red",
      "path": "DAM-1/Sistemas informáticos/Tema 5 - Sistemas Informáticos en Red/Tema 5 - Sistemas Informáticos en Red.md"
    },
    {
      "basename": "5.2.1 - Modelo OSI",
      "path": "DAM-1/Sistemas informáticos/Tema 5 - Sistemas Informáticos en Red/5.2.1 - Modelo OSI.md"
    },
    {
      "basename": "5.2 - Modelos de Referencia",
      "path": "DAM-1/Sistemas informáticos/Tema 5 - Sistemas Informáticos en Red/5.2 - Modelos de Referencia.md"
    },
    {
      "basename": "5.1.3 - Mapas Físicos y Lógicos",
      "path": "DAM-1/Sistemas informáticos/Tema 5 - Sistemas Informáticos en Red/5.1.3 - Mapas Físicos y Lógicos.md"
    },
    {
      "basename": "5.2.3 - Comparación OSI y TCP-IP",
      "path": "DAM-1/Sistemas informáticos/Tema 5 - Sistemas Informáticos en Red/5.2.3 - Comparación OSI y TCP-IP.md"
    },
    {
      "basename": "Sistemas informáticos",
      "path": "DAM-1/Sistemas informáticos/Sistemas informáticos.md"
    },
    {
      "basename": "5.6 - Monitorización y Simulación",
      "path": "DAM-1/Sistemas informáticos/Tema 5 - Sistemas Informáticos en Red/5.6 - Monitorización y Simulación.md"
    },
    {
      "basename": "Ejercicio",
      "path": "DAM-1/Sistemas informáticos/Tema 5 - Sistemas Informáticos en Red/Ejercicio.md"
    },
    {
      "basename": "5.6.1 y 5.6.2 - Monitorización y Simulación",
      "path": "DAM-1/Sistemas informáticos/Tema 5 - Sistemas Informáticos en Red/5.6.1 y 5.6.2 - Monitorización y Simulación.md"
    },
    {
      "basename": "5.4.3 y 5.4.4 - WAN y Conexión a Internet",
      "path": "DAM-1/Sistemas informáticos/Tema 5 - Sistemas Informáticos en Red/5.4.3 y 5.4.4 - WAN y Conexión a Internet.md"
    },
    {
      "basename": "5.5 - Configuración de Red",
      "path": "DAM-1/Sistemas informáticos/Tema 5 - Sistemas Informáticos en Red/5.5 - Configuración de Red.md"
    },
    {
      "basename": "5.4.2 - Redes Inalámbricas",
      "path": "DAM-1/Sistemas informáticos/Tema 5 - Sistemas Informáticos en Red/5.4.2 - Redes Inalámbricas.md"
    },
    {
      "basename": "5.4.1 - Redes Cableadas",
      "path": "DAM-1/Sistemas informáticos/Tema 5 - Sistemas Informáticos en Red/5.4.1 - Redes Cableadas.md"
    },
    {
      "basename": "5.4 - Conexión",
      "path": "DAM-1/Sistemas informáticos/Tema 5 - Sistemas Informáticos en Red/5.4 - Conexión.md"
    },
    {
      "basename": "5.3.5 - Subnetting",
      "path": "DAM-1/Sistemas informáticos/Tema 5 - Sistemas Informáticos en Red/5.3.5 - Subnetting.md"
    },
    {
      "basename": "5.3.6 - Servidores DHCP y DNS",
      "path": "DAM-1/Sistemas informáticos/Tema 5 - Sistemas Informáticos en Red/5.3.6 - Servidores DHCP y DNS.md"
    },
    {
      "basename": "5.3.4 - Puerta de Enlace",
      "path": "DAM-1/Sistemas informáticos/Tema 5 - Sistemas Informáticos en Red/5.3.4 - Puerta de Enlace.md"
    },
    {
      "basename": "5.3.2 - Máscara de Subred",
      "path": "DAM-1/Sistemas informáticos/Tema 5 - Sistemas Informáticos en Red/5.3.2 - Máscara de Subred.md"
    },
    {
      "basename": "5.3.3 - Clases de Redes IPv4",
      "path": "DAM-1/Sistemas informáticos/Tema 5 - Sistemas Informáticos en Red/5.3.3 - Clases de Redes IPv4.md"
    },
    {
      "basename": "5.3.1 - Direcciones IPv4 e IPv6",
      "path": "DAM-1/Sistemas informáticos/Tema 5 - Sistemas Informáticos en Red/5.3.1 - Direcciones IPv4 e IPv6.md"
    },
    {
      "basename": "5.3 - Direccionamiento IP",
      "path": "DAM-1/Sistemas informáticos/Tema 5 - Sistemas Informáticos en Red/5.3 - Direccionamiento IP.md"
    },
    {
      "basename": "5.2.4 - Protocolos Utilizados en las Redes",
      "path": "DAM-1/Sistemas informáticos/Tema 5 - Sistemas Informáticos en Red/5.2.4 - Protocolos Utilizados en las Redes.md"
    },
    {
      "basename": "5.1.1 - Protocolos y Estándares",
      "path": "DAM-1/Sistemas informáticos/Tema 5 - Sistemas Informáticos en Red/5.1.1 - Protocolos y Estándares.md"
    },
    {
      "basename": "5.1.2 - Tipos de Redes",
      "path": "DAM-1/Sistemas informáticos/Tema 5 - Sistemas Informáticos en Red/5.1.2 - Tipos de Redes.md"
    },
    {
      "basename": "5.1 - Redes Informáticas",
      "path": "DAM-1/Sistemas informáticos/Tema 5 - Sistemas Informáticos en Red/5.1 - Redes Informáticas.md"
    },
    {
      "basename": "Cosas Random",
      "path": "Cosas Random.md"
    },
    {
      "basename": "Examen Sistemas",
      "path": "Examen Sistemas.md"
    },
    {
      "basename": "Validación XML DTD y XSD",
      "path": "DAM-1/LenguajeMarcas/XML/Validación XML DTD y XSD.md"
    },
    {
      "basename": "XML",
      "path": "DAM-1/LenguajeMarcas/XML/XML.md"
    },
    {
      "basename": "LenguajeMarcas",
      "path": "DAM-1/LenguajeMarcas/LenguajeMarcas.md"
    },
    {
      "basename": "To-Do",
      "path": "To-Do.md"
    },
    {
      "basename": "GIT",
      "path": "DAM-1/Entornos de desarrollo/GIT.md"
    },
    {
      "basename": "Ejercicio UML",
      "path": "DAM-1/Entornos de desarrollo/Ejercicio UML.md"
    },
    {
      "basename": "Ejercicio 6",
      "path": "DAM-1/Entornos de desarrollo/Ejercicio 6.md"
    },
    {
      "basename": "Unidad 6 - Diseño orientado a objetos - Diagramas de comportamiento",
      "path": "DAM-1/Entornos de desarrollo/Unidad 6 - Diseño orientado a objetos - Diagramas de comportamiento.md"
    },
    {
      "basename": "Unidad 2 - Instalación y uso de entornos de desarrollo",
      "path": "DAM-1/Entornos de desarrollo/Unidad 2 - Instalación y uso de entornos de desarrollo.md"
    },
    {
      "basename": "Unidad 1 - Desarrollo de Software",
      "path": "DAM-1/Entornos de desarrollo/Unidad 1 - Desarrollo de Software.md"
    },
    {
      "basename": "Máquina de Van Neuman",
      "path": "DAM-1/Entornos de desarrollo/Máquina de Van Neuman.md"
    },
    {
      "basename": "HelloWorld",
      "path": "DAM-1/Entornos de desarrollo/HelloWorld.md"
    },
    {
      "basename": "Trabajo UR4",
      "path": "DAM-1/Sistemas informáticos/Trabajo UR4/Trabajo UR4.md"
    },
    {
      "basename": "Entornos de desarrollo",
      "path": "DAM-1/Entornos de desarrollo/Entornos de desarrollo.md"
    },
    {
      "basename": "DAM-1",
      "path": "DAM-1/DAM-1.md"
    },
    {
      "basename": "Práctica Python",
      "path": "DAM-1/Práctica Python.md"
    },
    {
      "basename": "Programación",
      "path": "DAM-1/Programación/Programación.md"
    },
    {
      "basename": "Unidad 5 - Lectura y escritura de archivos en Java",
      "path": "DAM-1/Programación/Teoría/Unidad 5 - Lectura y escritura de archivos en Java/Unidad 5 - Lectura y escritura de archivos en Java.md"
    },
    {
      "basename": "Diccionarios",
      "path": "DAM-1/Programación/Python/Diccionarios.md"
    },
    {
      "basename": "Views y delimitadores en MySQL",
      "path": "DAM-1/Bases de datos/Unit 5 - Triggers/Views y delimitadores en MySQL.md"
    },
    {
      "basename": "Unit 5 - Triggers",
      "path": "DAM-1/Bases de datos/Unit 5 - Triggers/Unit 5 - Triggers.md"
    },
    {
      "basename": "Introducción a Triggers en MySQL",
      "path": "DAM-1/Bases de datos/Unit 5 - Triggers/Introducción a Triggers en MySQL.md"
    }
  ],
  "omittedPaths": [],
  "omittedTags": [],
  "updateOn": "file-open",
  "omitBookmarks": false
}